my_tool_package/__init__.py
my_tool_package/tools/__init__.py
my_tool_package/tools/my_tool_1.py
my_tool_package/tools/my_tool_2.py
my_tool_package/tools/tool_with_custom_llm_type.py
my_tool_package/tools/tool_with_custom_strong_type_connection.py
my_tool_package/tools/tool_with_dynamic_list_input.py
my_tool_package/tools/tool_with_dynamic_list_input_error.py
my_tool_package/tools/tool_with_enabled_by_value.py
my_tool_package/tools/tool_with_file_path_input.py
my_tool_package/tools/utils.py
my_tool_package/yamls/my_tool_1.yaml
my_tool_package/yamls/my_tool_2.yaml
my_tool_package/yamls/tool_with_custom_llm_type.yaml
my_tool_package/yamls/tool_with_custom_strong_type_connection.yaml
my_tool_package/yamls/tool_with_dynamic_list_input.yaml
my_tool_package/yamls/tool_with_dynamic_list_input_error.yaml
my_tool_package/yamls/tool_with_enabled_by_value.yaml
my_tool_package/yamls/tool_with_file_path_input.yaml
tests/__init__.py
tests/test_my_tool_1.py
tests/test_my_tool_2.py
tests/test_tool_with_custom_llm_type.py
tests/test_tool_with_custom_strong_type_connection.py
tests/test_tool_with_dynamic_input.py
tests/test_tool_with_enabled_by_value.py
tests/test_tool_with_file_path_input.py
my_tools_package_dynamic_list-0.0.6.post1.dist-info/METADATA
my_tools_package_dynamic_list-0.0.6.post1.dist-info/WHEEL
my_tools_package_dynamic_list-0.0.6.post1.dist-info/entry_points.txt
my_tools_package_dynamic_list-0.0.6.post1.dist-info/top_level.txt
my_tools_package_dynamic_list-0.0.6.post1.dist-info/RECORD
