Metadata-Version: 2.1
Name: my-tools-package-dynamic-list
Version: 0.0.6.post1
Summary: This is my tools package
